quackdoor/__init__.py
quackdoor/__main__.py
quackdoor/builder.py
quackdoor/encoder.py
quackdoor/payload.py
quackdoor/templates.py
quackdoor-0.1.1.dist-info/licenses/LICENSE
quackdoor-0.1.1.dist-info/METADATA
quackdoor-0.1.1.dist-info/WHEEL
quackdoor-0.1.1.dist-info/entry_points.txt
quackdoor-0.1.1.dist-info/top_level.txt
quackdoor-0.1.1.dist-info/RECORD
