Metadata-Version: 2.4
Name: quackdoor
Version: 0.1.1
Summary: A tool to embed python code into a runnable DuckyScript on mac os
Project-URL: Repository, https://github.com/mah5057/quackdoor
Requires-Python: >=3.8
License-File: LICENSE
Dynamic: license-file
